Workbook
Name Slicer_Month: #N/A
Name Slicer_Platform: #N/A
Name Slicer_Year: #N/A

Sheet Data
A1: Order ID | B1: Order Date | C1: Customer Name | D1: City | E1: Product Name | F1: Product | G1: Brand | H1: Unit Price | I1: Quantity | J1: Discount (%) | K1: Subtotal | L1: Discount Amount | M1: Total Sales | N1: Shipping Fee | O1: Grand Total | P1: Payment Method | Q1: Order Status | R1: Platform | S1: Customer Rating | T1: Jenis Kelamin | U1: Month | V1: Year | W1: Sort
A2: ORD01491 | B2: 45658.069 | C2: Hana Wijaya | D2: Sorong | E2: Beras - Brand C | F2: {=_xlfn.TEXTSPLIT(E2," - ")} -> Beras | G2: Brand C | H2: 16000 | I2: 5 | J2: 0 | K2: =H2*I2 -> 80000 | L2: =K2*J2% -> 0 | M2: =K2-L2 -> 80000 | N2: 87000 | O2: =M2+N2 -> 167000 | P2: COD | Q2: =VLOOKUP(A2,Status!A:B,2,0) -> Completed | R2: Toko Orange | S2: 4 | T2: Perempuan | U2: =TEXT(B2,"MMM") -> Jan | V2: =YEAR(B2) -> 2025 | W2: {=_xlfn.IFS(U2="January",1,U2="February",2,U2="March",3,U2="April",4,U2="May",5,U2="June",6,U2="July",7,U2="August",8,U2="September",9,U2="October",10,U2="November",11,U2="December",12)} -> #N/A
A3: ORD00442 | B3: 45658.182 | C3: Gita Kusuma | D3: Pekanbaru | E3: Daging Ayam - Brand B | F3: {=_xlfn.TEXTSPLIT(E3," - ")} -> Daging Ayam | G3: Brand B | H3: 40000 | I3: 4 | J3: 20 | K3: =H3*I3 -> 160000 | L3: =K3*J3% -> 32000 | M3: =K3-L3 -> 128000 | N3: 49000 | O3: =M3+N3 -> 177000 | P3: Kartu Kredit | Q3: =VLOOKUP(A3,Status!A:B,2,0) -> Completed | R3: Toko Hijau | S3: 4 | T3: Perempuan | U3: =TEXT(B3,"MMM") -> Jan | V3: =YEAR(B3) -> 2025 | W3: {=_xlfn.IFS(U3="January",1,U3="February",2,U3="March",3,U3="April",4,U3="May",5,U3="June",6,U3="July",7,U3="August",8,U3="September",9,U3="October",10,U3="November",11,U3="December",12)} -> #N/A
A4: ORD00223 | B4: 45658.316 | C4: Aulia Syahputra | D4: Medan | E4: Tepung Terigu - Brand B | F4: {=_xlfn.TEXTSPLIT(E4," - ")} -> Tepung Terigu | G4: Brand B | H4: 12000 | I4: 4 | J4: 20 | K4: =H4*I4 -> 48000 | L4: =K4*J4% -> 9600 | M4: =K4-L4 -> 38400 | N4: 79000 | O4: =M4+N4 -> 117400 | P4: e-Wallet | Q4: =VLOOKUP(A4,Status!A:B,2,0) -> Completed | R4: Toko Ungu | S4: 2 | T4: Perempuan | U4: =TEXT(B4,"MMM") -> Jan | V4: =YEAR(B4) -> 2025 | W4: {=_xlfn.IFS(U4="January",1,U4="February",2,U4="March",3,U4="April",4,U4="May",5,U4="June",6,U4="July",7,U4="August",8,U4="September",9,U4="October",10,U4="November",11,U4="December",12)} -> #N/A
A5: ORD00724 | B5: 45658.476 | C5: Vina Maulana | D5: Wamena | E5: Bawang Merah - Brand A | F5: {=_xlfn.TEXTSPLIT(E5," - ")} -> Bawang Merah | G5: Brand A | H5: 30000 | I5: 3 | J5: 20 | K5: =H5*I5 -> 90000 | L5: =K5*J5% -> 18000 | M5: =K5-L5 -> 72000 | N5: 15000 | O5: =M5+N5 -> 87000 | P5: e-Wallet | Q5: =VLOOKUP(A5,Status!A:B,2,0) -> Completed | R5: Toko Biru | S5: 4 | T5: Perempuan | U5: =TEXT(B5,"MMM") -> Jan | V5: =YEAR(B5) -> 2025 | W5: {=_xlfn.IFS(U5="January",1,U5="February",2,U5="March",3,U5="April",4,U5="May",5,U5="June",6,U5="July",7,U5="August",8,U5="September",9,U5="October",10,U5="November",11,U5="December",12)} -> #N/A
A6: ORD01549 | B6: 45658.607 | C6: Fitri Ramadhani | D6: Surabaya | E6: Telur Ayam - Brand C | F6: {=_xlfn.TEXTSPLIT(E6," - ")} -> Telur Ayam | G6: Brand C | H6: 28000 | I6: 5 | J6: 5 | K6: =H6*I6 -> 140000 | L6: =K6*J6% -> 7000 | M6: =K6-L6 -> 133000 | N6: 74000 | O6: =M6+N6 -> 207000 | P6: COD | Q6: =VLOOKUP(A6,Status!A:B,2,0) -> Completed | R6: TokTok | S6: 3 | T6: Perempuan | U6: =TEXT(B6,"MMM") -> Jan | V6: =YEAR(B6) -> 2025 | W6: {=_xlfn.IFS(U6="January",1,U6="February",2,U6="March",3,U6="April",4,U6="May",5,U6="June",6,U6="July",7,U6="August",8,U6="September",9,U6="October",10,U6="November",11,U6="December",12)} -> #N/A
A7: ORD01854 | B7: 45658.663 | C7: Tono Kurniawan | D7: Semarang | E7: Garam - Brand C | F7: {=_xlfn.TEXTSPLIT(E7," - ")} -> Garam | G7: Brand C | H7: 6000 | I7: 4 | J7: 10 | K7: =H7*I7 -> 24000 | L7: =K7*J7% -> 2400 | M7: =K7-L7 -> 21600 | N7: 76000 | O7: =M7+N7 -> 97600 | P7: Transfer Bank | Q7: =VLOOKUP(A7,Status!A:B,2,0) -> Returned | R7: Toko Orange | S7: 3 | T7: Laki-laki | U7: =TEXT(B7,"MMM") -> Jan | V7: =YEAR(B7) -> 2025 | W7: {=_xlfn.IFS(U7="January",1,U7="February",2,U7="March",3,U7="April",4,U7="May",5,U7="June",6,U7="July",7,U7="August",8,U7="September",9,U7="October",10,U7="November",11,U7="December",12)} -> #N/A
A8: ORD00642 | B8: 45658.794 | C8: Hendra Syahputra | D8: Wamena | E8: Telur Ayam - Brand A | F8: {=_xlfn.TEXTSPLIT(E8," - ")} -> Telur Ayam | G8: Brand A | H8: 22000 | I8: 1 | J8: 10 | K8: =H8*I8 -> 22000 | L8: =K8*J8% -> 2200 | M8: =K8-L8 -> 19800 | N8: 15000 | O8: =M8+N8 -> 34800 | P8: COD | Q8: =VLOOKUP(A8,Status!A:B,2,0) -> Completed | R8: Toko Ungu | S8: 1 | T8: Laki-laki | U8: =TEXT(B8,"MMM") -> Jan | V8: =YEAR(B8) -> 2025 | W8: {=_xlfn.IFS(U8="January",1,U8="February",2,U8="March",3,U8="April",4,U8="May",5,U8="June",6,U8="July",7,U8="August",8,U8="September",9,U8="October",10,U8="November",11,U8="December",12)} -> #N/A
A9: ORD01352 | B9: 45658.815 | C9: Indra Halim | D9: Tanjung Selor | E9: Gula Pasir - Brand C | F9: {=_xlfn.TEXTSPLIT(E9," - ")} -> Gula Pasir | G9: Brand C | H9: 18000 | I9: 1 | J9: 5 | K9: =H9*I9 -> 18000 | L9: =K9*J9% -> 900 | M9: =K9-L9 -> 17100 | N9: 26000 | O9: =M9+N9 -> 43100 | P9: Transfer Bank | Q9: =VLOOKUP(A9,Status!A:B,2,0) -> Completed | R9: Toko Ungu | S9: 5 | T9: Laki-laki | U9: =TEXT(B9,"MMM") -> Jan | V9: =YEAR(B9) -> 2025 | W9: {=_xlfn.IFS(U9="January",1,U9="February",2,U9="March",3,U9="April",4,U9="May",5,U9="June",6,U9="July",7,U9="August",8,U9="September",9,U9="October",10,U9="November",11,U9="December",12)} -> #N/A
A10: ORD00616 | B10: 45658.85 | C10: Wahyu Hidayat | D10: Wamena | E10: Garam - Brand A | F10: {=_xlfn.TEXTSPLIT(E10," - ")} -> Garam | G10: Brand A | H10: 4000 | I10: 1 | J10: 20 | K10: =H10*I10 -> 4000 | L10: =K10*J10% -> 800 | M10: =K10-L10 -> 3200 | N10: 15000 | O10: =M10+N10 -> 18200 | P10: e-Wallet | Q10: =VLOOKUP(A10,Status!A:B,2,0) -> Completed | R10: TokTok | S10: 3 | T10: Laki-laki | U10: =TEXT(B10,"MMM") -> Jan | V10: =YEAR(B10) -> 2025 | W10: {=_xlfn.IFS(U10="January",1,U10="February",2,U10="March",3,U10="April",4,U10="May",5,U10="June",6,U10="July",7,U10="August",8,U10="September",9,U10="October",10,U10="November",11,U10="December",12)} -> #N/A
A11: ORD00528 | B11: 45659.142 | C11: Zahra Setiawan | D11: Banjarbaru | E11: Gula Pasir - Brand B | F11: {=_xlfn.TEXTSPLIT(E11," - ")} -> Gula Pasir | G11: Brand B | H11: 17000 | I11: 1 | J11: 10 | K11: =H11*I11 -> 17000 | L11: =K11*J11% -> 1700 | M11: =K11-L11 -> 15300 | N11: 55000 | O11: =M11+N11 -> 70300 | P11: Kartu Kredit | Q11: =VLOOKUP(A11,Status!A:B,2,0) -> Returned | R11: Toko Orange | S11: 2 | T11: Perempuan | U11: =TEXT(B11,"MMM") -> Jan | V11: =YEAR(B11) -> 2025 | W11: {=_xlfn.IFS(U11="January",1,U11="February",2,U11="March",3,U11="April",4,U11="May",5,U11="June",6,U11="July",7,U11="August",8,U11="September",9,U11="October",10,U11="November",11,U11="December",12)} -> #N/A
A12: ORD00809 | B12: 45659.26 | C12: Yani Ananda | D12: Mataram | E12: Beras - Brand B | F12: {=_xlfn.TEXTSPLIT(E12," - ")} -> Beras | G12: Brand B | H12: 15000 | I12: 2 | J12: 0 | K12: =H12*I12 -> 30000 | L12: =K12*J12% -> 0 | M12: =K12-L12 -> 30000 | N12: 56000 | O12: =M12+N12 -> 86000 | P12: e-Wallet | Q12: =VLOOKUP(A12,Status!A:B,2,0) -> Completed | R12: Toko Hijau | S12: 1 | T12: Perempuan | U12: =TEXT(B12,"MMM") -> Jan | V12: =YEAR(B12) -> 2025 | W12: {=_xlfn.IFS(U12="January",1,U12="February",2,U12="March",3,U12="April",4,U12="May",5,U12="June",6,U12="July",7,U12="August",8,U12="September",9,U12="October",10,U12="November",11,U12="December",12)} -> #N/A
A13: ORD00413 | B13: 45659.448 | C13: Kartika Saputra | D13: Palu | E13: Gula Pasir - Brand A | F13: {=_xlfn.TEXTSPLIT(E13," - ")} -> Gula Pasir | G13: Brand A | H13: 16000 | I13: 2 | J13: 10 | K13: =H13*I13 -> 32000 | L13: =K13*J13% -> 3200 | M13: =K13-L13 -> 28800 | N13: 67000 | O13: =M13+N13 -> 95800 | P13: Kartu Kredit | Q13: =VLOOKUP(A13,Status!A:B,2,0) -> Completed | R13: Toko Ungu | S13: 3 | T13: Perempuan | U13: =TEXT(B13,"MMM") -> Jan | V13: =YEAR(B13) -> 2025 | W13: {=_xlfn.IFS(U13="January",1,U13="February",2,U13="March",3,U13="April",4,U13="May",5,U13="June",6,U13="July",7,U13="August",8,U13="September",9,U13="October",10,U13="November",11,U13="December",12)} -> #N/A
... A2001: ORD01065 | B2001: 45657.957 | C2001: Dewi Budiman | D2001: Kupang | E2001: Garam - Brand C | F2001: {=_xlfn.TEXTSPLIT(E2001," - ")} -> Garam | G2001: Brand C | H2001: 6000 | I2001: 3 | J2001: 20 | K2001: =H2001*I2001 -> 18000 | L2001: =K2001*J2001% -> 3600 | M2001: =K2001-L2001 -> 14400 | N2001: 21000 | O2001: =M2001+N2001 -> 35400 | P2001: COD | Q2001: =VLOOKUP(A2001,Status!A:B,2,0) -> Completed | R2001: TokTok | S2001: 5 | T2001: Perempuan | U2001: =TEXT(B2001,"MMM") -> Dec | V2001: =YEAR(B2001) -> 2024 | W2001: {=_xlfn.IFS(U2001="January",1,U2001="February",2,U2001="March",3,U2001="April",4,U2001="May",5,U2001="June",6,U2001="July",7,U2001="August",8,U2001="September",9,U2001="October",10,U2001="November",11,U2001="December",12)} -> #N/A

Sheet Status
A1: Order ID | B1: Order Status
A2: ORD00001 | B2: Returned
A3: ORD00002 | B3: Completed
A4: ORD00003 | B4: Returned
A5: ORD00004 | B5: Shipped
A6: ORD00005 | B6: Cancelled
A7: ORD00006 | B7: Completed
A8: ORD00007 | B8: Completed
A9: ORD00008 | B9: Returned
A10: ORD00009 | B10: Completed
A11: ORD00010 | B11: Completed
A12: ORD00011 | B12: Completed
... A1867: ORD01866 | B1867: Completed

Sheet Tugas
B2: Latihan
B4: Jika kalian adalah pemilik toko sembako dan dengan data yang sudah teman-teman olah selama ini, coba berikan 3 pertanyaan apa yang mau kalian tanyakan dan bisa dijawab oleh data ini.
C5: 3 Pertanyaan :
C6: 1 | D6: Produk apa yang menghasilkan penjualan (omzet) paling besar?
C7: 2 | D7: Pada bulan apa penjualan tertinggi?
C8: 3 | D8: Siapa pelanggan yang paling sering membeli atau memberikan kontribusi terbesar?
B10: Setelah itu buatlah dashboard di Excel dengan syarat seperti ini:
C11: • | D11: Minimal ada 1 Scorecard (menunjukkan metrics/kalkulasi utama)
C12: • | D12: Minimal ada 3 grafik visual yang menunjukkan 3 pertanyaan yang sebelumnya telah dibuat (terserah mau warna/visualnya seperti apa, silahkan berkreasi).
C13: • | D13: Minimal 1 slicer (untuk bisa filter data dari semua grafik dan scorecard agar bisa mendapat informasi lain).
B15: Tidak ada jawaban benar/salah, silahkan berkreasi. Jika bingung silahkan googling dengan keyword (contoh layout dashboard).

Sheet Jawab
B2: Product/Brand | C2: Brand A | D2: Brand B | E2: Brand C
B3: {=_xlfn._xlws.SORT(_xlfn.UNIQUE(Data!F2:F2001))} -> Bawang Merah | C3: =SUMIFS(Data!$M:$M,Data!$F:$F,Jawab!$B3,Data!$G:$G,Jawab!C$2) -> 5319000 | D3: =SUMIFS(Data!$M:$M,Data!$F:$F,Jawab!$B3,Data!$G:$G,Jawab!D$2) -> 6672750 | E3: =SUMIFS(Data!$M:$M,Data!$F:$F,Jawab!$B3,Data!$G:$G,Jawab!E$2) -> 5310000
B4: Beras | C4: =SUMIFS(Data!$M:$M,Data!$F:$F,Jawab!$B4,Data!$G:$G,Jawab!C$2) -> 2762900 | D4: =SUMIFS(Data!$M:$M,Data!$F:$F,Jawab!$B4,Data!$G:$G,Jawab!D$2) -> 2838750 | E4: =SUMIFS(Data!$M:$M,Data!$F:$F,Jawab!$B4,Data!$G:$G,Jawab!E$2) -> 2801600
B5: Daging Ayam | C5: =SUMIFS(Data!$M:$M,Data!$F:$F,Jawab!$B5,Data!$G:$G,Jawab!C$2) -> 6650000 | D5: =SUMIFS(Data!$M:$M,Data!$F:$F,Jawab!$B5,Data!$G:$G,Jawab!D$2) -> 9480000 | E5: =SUMIFS(Data!$M:$M,Data!$F:$F,Jawab!$B5,Data!$G:$G,Jawab!E$2) -> 10075500 | X5: Total Customer | Z5: Total Sale
B6: Garam | C6: =SUMIFS(Data!$M:$M,Data!$F:$F,Jawab!$B6,Data!$G:$G,Jawab!C$2) -> 801000 | D6: =SUMIFS(Data!$M:$M,Data!$F:$F,Jawab!$B6,Data!$G:$G,Jawab!D$2) -> 920250 | E6: =SUMIFS(Data!$M:$M,Data!$F:$F,Jawab!$B6,Data!$G:$G,Jawab!E$2) -> 1436100 | X6: =COUNTA(_xlfn.UNIQUE(Data!C2:C2001))&" Orang" -> 396 Orang | Z6: =SUM(Data!M2:M2001) -> 128487050
B7: Gula Pasir | C7: =SUMIFS(Data!$M:$M,Data!$F:$F,Jawab!$B7,Data!$G:$G,Jawab!C$2) -> 3150400 | D7: =SUMIFS(Data!$M:$M,Data!$F:$F,Jawab!$B7,Data!$G:$G,Jawab!D$2) -> 3110150 | E7: =SUMIFS(Data!$M:$M,Data!$F:$F,Jawab!$B7,Data!$G:$G,Jawab!E$2) -> 3887100
B8: Minyak Goreng | C8: =SUMIFS(Data!$M:$M,Data!$F:$F,Jawab!$B8,Data!$G:$G,Jawab!C$2) -> 3612000 | D8: =SUMIFS(Data!$M:$M,Data!$F:$F,Jawab!$B8,Data!$G:$G,Jawab!D$2) -> 3328600 | E8: =SUMIFS(Data!$M:$M,Data!$F:$F,Jawab!$B8,Data!$G:$G,Jawab!E$2) -> 2772000
B9: Susu Bubuk | C9: =SUMIFS(Data!$M:$M,Data!$F:$F,Jawab!$B9,Data!$G:$G,Jawab!C$2) -> 8835750 | D9: =SUMIFS(Data!$M:$M,Data!$F:$F,Jawab!$B9,Data!$G:$G,Jawab!D$2) -> 10135000 | E9: =SUMIFS(Data!$M:$M,Data!$F:$F,Jawab!$B9,Data!$G:$G,Jawab!E$2) -> 11200750
B10: Telur Ayam | C10: =SUMIFS(Data!$M:$M,Data!$F:$F,Jawab!$B10,Data!$G:$G,Jawab!C$2) -> 4730000 | D10: =SUMIFS(Data!$M:$M,Data!$F:$F,Jawab!$B10,Data!$G:$G,Jawab!D$2) -> 5693750 | E10: =SUMIFS(Data!$M:$M,Data!$F:$F,Jawab!$B10,Data!$G:$G,Jawab!E$2) -> 5640600
B11: Tepung Terigu | C11: =SUMIFS(Data!$M:$M,Data!$F:$F,Jawab!$B11,Data!$G:$G,Jawab!C$2) -> 1846000 | D11: =SUMIFS(Data!$M:$M,Data!$F:$F,Jawab!$B11,Data!$G:$G,Jawab!D$2) -> 2253600 | E11: =SUMIFS(Data!$M:$M,Data!$F:$F,Jawab!$B11,Data!$G:$G,Jawab!E$2) -> 3223500
B16: Month/Year | C16: Tahun 2024 | D16: Tahun 2025
B17: {=_xlfn.UNIQUE(Data!U2:U2001)} -> Jan | C17: =SUMIFS(Data!$M:$M,Data!$U:$U,Jawab!$B17,Data!$V:$V,2024) -> 0 | D17: =SUMIFS(Data!$M:$M,Data!$U:$U,Jawab!$B17,Data!$V:$V,2025) -> 10915900
B18: Feb | C18: =SUMIFS(Data!$M:$M,Data!$U:$U,Jawab!$B18,Data!$V:$V,2024) -> 0 | D18: =SUMIFS(Data!$M:$M,Data!$U:$U,Jawab!$B18,Data!$V:$V,2025) -> 8697300
B19: Mar | C19: =SUMIFS(Data!$M:$M,Data!$U:$U,Jawab!$B19,Data!$V:$V,2024) -> 0 | D19: =SUMIFS(Data!$M:$M,Data!$U:$U,Jawab!$B19,Data!$V:$V,2025) -> 10043950
B20: Apr | C20: =SUMIFS(Data!$M:$M,Data!$U:$U,Jawab!$B20,Data!$V:$V,2024) -> 0 | D20: =SUMIFS(Data!$M:$M,Data!$U:$U,Jawab!$B20,Data!$V:$V,2025) -> 10587550
B21: May | C21: =SUMIFS(Data!$M:$M,Data!$U:$U,Jawab!$B21,Data!$V:$V,2024) -> 0 | D21: =SUMIFS(Data!$M:$M,Data!$U:$U,Jawab!$B21,Data!$V:$V,2025) -> 11359600
B22: Jun | C22: =SUMIFS(Data!$M:$M,Data!$U:$U,Jawab!$B22,Data!$V:$V,2024) -> 0 | D22: =SUMIFS(Data!$M:$M,Data!$U:$U,Jawab!$B22,Data!$V:$V,2025) -> 11708650
B23: Jul | C23: =SUMIFS(Data!$M:$M,Data!$U:$U,Jawab!$B23,Data!$V:$V,2024) -> 0 | D23: =SUMIFS(Data!$M:$M,Data!$U:$U,Jawab!$B23,Data!$V:$V,2025) -> 12385950
B24: Aug | C24: =SUMIFS(Data!$M:$M,Data!$U:$U,Jawab!$B24,Data!$V:$V,2024) -> 0 | D24: =SUMIFS(Data!$M:$M,Data!$U:$U,Jawab!$B24,Data!$V:$V,2025) -> 11002900
B25: Sep | C25: =SUMIFS(Data!$M:$M,Data!$U:$U,Jawab!$B25,Data!$V:$V,2024) -> 6957800 | D25: =SUMIFS(Data!$M:$M,Data!$U:$U,Jawab!$B25,Data!$V:$V,2025) -> 5004950
B26: Oct | C26: =SUMIFS(Data!$M:$M,Data!$U:$U,Jawab!$B26,Data!$V:$V,2024) -> 10583650 | D26: =SUMIFS(Data!$M:$M,Data!$U:$U,Jawab!$B26,Data!$V:$V,2025) -> 0
B27: Nov | C27: =SUMIFS(Data!$M:$M,Data!$U:$U,Jawab!$B27,Data!$V:$V,2024) -> 10883500 | D27: =SUMIFS(Data!$M:$M,Data!$U:$U,Jawab!$B27,Data!$V:$V,2025) -> 0
B28: Dec | C28: =SUMIFS(Data!$M:$M,Data!$U:$U,Jawab!$B28,Data!$V:$V,2024) -> 8355350 | D28: =SUMIFS(Data!$M:$M,Data!$U:$U,Jawab!$B28,Data!$V:$V,2025) -> 0
B33: Nama Cust | C33: Transaksi 2024 | D33: Transaksi 2025 | E33: Total Transaksi | G33: Nama Cust | H33: Sale 2024 | I33: Sale 2025 | J33: Total Sale
B34: Sari Puspita | C34: =COUNTIFS(Data!C:C,B34,Data!V:V,2024) -> 4 | D34: =COUNTIFS(Data!C:C,B34,Data!V:V,2025) -> 14 | E34: =C34+D34 -> 18 | G34: Citra Maulana | H34: =SUMIFS(Data!M:M,Data!C:C,G34,Data!V:V,2024) -> 320600 | I34: =SUMIFS(Data!M:M,Data!C:C,G34,Data!V:V,2025) -> 885600 | J34: =H34+I34 -> 1206200
B35: Kartika Saputra | C35: =COUNTIFS(Data!C:C,B35,Data!V:V,2024) -> 2 | D35: =COUNTIFS(Data!C:C,B35,Data!V:V,2025) -> 16 | E35: =C35+D35 -> 18 | G35: Sari Puspita | H35: =SUMIFS(Data!M:M,Data!C:C,G35,Data!V:V,2024) -> 340400 | I35: =SUMIFS(Data!M:M,Data!C:C,G35,Data!V:V,2025) -> 857350 | J35: =H35+I35 -> 1197750
B36: Hana Nugroho | C36: =COUNTIFS(Data!C:C,B36,Data!V:V,2024) -> 4 | D36: =COUNTIFS(Data!C:C,B36,Data!V:V,2025) -> 13 | E36: =C36+D36 -> 17 | G36: Yani Ananda | H36: =SUMIFS(Data!M:M,Data!C:C,G36,Data!V:V,2024) -> 296000 | I36: =SUMIFS(Data!M:M,Data!C:C,G36,Data!V:V,2025) -> 840350 | J36: =H36+I36 -> 1136350
B37: Ani Fauziah | C37: =COUNTIFS(Data!C:C,B37,Data!V:V,2024) -> 8 | D37: =COUNTIFS(Data!C:C,B37,Data!V:V,2025) -> 8 | E37: =C37+D37 -> 16 | G37: Hana Nugroho | H37: =SUMIFS(Data!M:M,Data!C:C,G37,Data!V:V,2024) -> 99200 | I37: =SUMIFS(Data!M:M,Data!C:C,G37,Data!V:V,2025) -> 968000 | J37: =H37+I37 -> 1067200
B38: Ani Hidayat | C38: =COUNTIFS(Data!C:C,B38,Data!V:V,2024) -> 4 | D38: =COUNTIFS(Data!C:C,B38,Data!V:V,2025) -> 10 | E38: =C38+D38 -> 14 | G38: Ani Hidayat | H38: =SUMIFS(Data!M:M,Data!C:C,G38,Data!V:V,2024) -> 340900 | I38: =SUMIFS(Data!M:M,Data!C:C,G38,Data!V:V,2025) -> 665400 | J38: =H38+I38 -> 1006300
B39: Yani Ananda | C39: =COUNTIFS(Data!C:C,B39,Data!V:V,2024) -> 3 | D39: =COUNTIFS(Data!C:C,B39,Data!V:V,2025) -> 10 | E39: =C39+D39 -> 13 | G39: Ani Fauziah | H39: =SUMIFS(Data!M:M,Data!C:C,G39,Data!V:V,2024) -> 530500 | I39: =SUMIFS(Data!M:M,Data!C:C,G39,Data!V:V,2025) -> 436800 | J39: =H39+I39 -> 967300
B40: Zahra Budiman | C40: =COUNTIFS(Data!C:C,B40,Data!V:V,2024) -> 3 | D40: =COUNTIFS(Data!C:C,B40,Data!V:V,2025) -> 10 | E40: =C40+D40 -> 13 | G40: Zahra Budiman | H40: =SUMIFS(Data!M:M,Data!C:C,G40,Data!V:V,2024) -> 285500 | I40: =SUMIFS(Data!M:M,Data!C:C,G40,Data!V:V,2025) -> 661800 | J40: =H40+I40 -> 947300
B41: Clara Utami | C41: =COUNTIFS(Data!C:C,B41,Data!V:V,2024) -> 5 | D41: =COUNTIFS(Data!C:C,B41,Data!V:V,2025) -> 8 | E41: =C41+D41 -> 13 | G41: Aulia Iskandar | H41: =SUMIFS(Data!M:M,Data!C:C,G41,Data!V:V,2024) -> 312000 | I41: =SUMIFS(Data!M:M,Data!C:C,G41,Data!V:V,2025) -> 585600 | J41: =H41+I41 -> 897600
B42: Aulia Iskandar | C42: =COUNTIFS(Data!C:C,B42,Data!V:V,2024) -> 6 | D42: =COUNTIFS(Data!C:C,B42,Data!V:V,2025) -> 6 | E42: =C42+D42 -> 12 | G42: Clara Utami | H42: =SUMIFS(Data!M:M,Data!C:C,G42,Data!V:V,2024) -> 281000 | I42: =SUMIFS(Data!M:M,Data!C:C,G42,Data!V:V,2025) -> 614900 | J42: =H42+I42 -> 895900
B43: Dewi Setiawan | C43: =COUNTIFS(Data!C:C,B43,Data!V:V,2024) -> 4 | D43: =COUNTIFS(Data!C:C,B43,Data!V:V,2025) -> 8 | E43: =C43+D43 -> 12 | G43: Zahra Kurniawan | H43: =SUMIFS(Data!M:M,Data!C:C,G43,Data!V:V,2024) -> 281600 | I43: =SUMIFS(Data!M:M,Data!C:C,G43,Data!V:V,2025) -> 577650 | J43: =H43+I43 -> 859250
B44: Citra Maulana | C44: =COUNTIFS(Data!C:C,B44,Data!V:V,2024) -> 4 | D44: =COUNTIFS(Data!C:C,B44,Data!V:V,2025) -> 7 | E44: =C44+D44 -> 11 | G44: Nanda Iskandar | H44: =SUMIFS(Data!M:M,Data!C:C,G44,Data!V:V,2024) -> 302500 | I44: =SUMIFS(Data!M:M,Data!C:C,G44,Data!V:V,2025) -> 543600 | J44: =H44+I44 -> 846100
B45: Dewi Hidayat | C45: =COUNTIFS(Data!C:C,B45,Data!V:V,2024) -> 2 | D45: =COUNTIFS(Data!C:C,B45,Data!V:V,2025) -> 9 | E45: =C45+D45 -> 11 | G45: Dewi Hidayat | H45: =SUMIFS(Data!M:M,Data!C:C,G45,Data!V:V,2024) -> 205200 | I45: =SUMIFS(Data!M:M,Data!C:C,G45,Data!V:V,2025) -> 619600 | J45: =H45+I45 -> 824800
... B429: Budi Puspita | C429: =COUNTIFS(Data!C:C,B429,Data!V:V,2024) -> 0 | D429: =COUNTIFS(Data!C:C,B429,Data!V:V,2025) -> 1 | E429: =C429+D429 -> 1 | G429: Budi Puspita | H429: =SUMIFS(Data!M:M,Data!C:C,G429,Data!V:V,2024) -> 0 | I429: =SUMIFS(Data!M:M,Data!C:C,G429,Data!V:V,2025) -> 16150 | J429: =H429+I429 -> 16150

Sheet Master Data
A1: Order ID | B1: Order Date | C1: Customer Name | D1: City | E1: Product Name | F1: Product | G1: Brand | H1: Unit Price | I1: Quantity | J1: Discount (%) | K1: Subtotal | L1: Discount Amount | M1: Total Sales | N1: Shipping Fee | O1: Grand Total | P1: Payment Method | Q1: Order Status | R1: Platform | S1: Customer Rating | T1: Jenis Kelamin | U1: Month | V1: Year | W1: Sort
A2: ORD01491 | B2: 45658.069 | C2: Hana Wijaya | D2: Sorong | E2: Beras - Brand C | F2: Beras | G2: Brand C | H2: 16000 | I2: 5 | J2: 0 | K2: 80000 | L2: 0 | M2: 80000 | N2: 87000 | O2: 167000 | P2: COD | Q2: Completed | R2: Toko Orange | S2: 4 | T2: Perempuan | U2: January | V2: 2025 | W2: 1
A3: ORD00442 | B3: 45658.182 | C3: Gita Kusuma | D3: Pekanbaru | E3: Daging Ayam - Brand B | F3: Daging Ayam | G3: Brand B | H3: 40000 | I3: 4 | J3: 20 | K3: 160000 | L3: 32000 | M3: 128000 | N3: 49000 | O3: 177000 | P3: Kartu Kredit | Q3: Completed | R3: Toko Hijau | S3: 4 | T3: Perempuan | U3: January | V3: 2025 | W3: 1
A4: ORD00223 | B4: 45658.316 | C4: Aulia Syahputra | D4: Medan | E4: Tepung Terigu - Brand B | F4: Tepung Terigu | G4: Brand B | H4: 12000 | I4: 4 | J4: 20 | K4: 48000 | L4: 9600 | M4: 38400 | N4: 79000 | O4: 117400 | P4: e-Wallet | Q4: Completed | R4: Toko Ungu | S4: 2 | T4: Perempuan | U4: January | V4: 2025 | W4: 1
A5: ORD00724 | B5: 45658.476 | C5: Vina Maulana | D5: Wamena | E5: Bawang Merah - Brand A | F5: Bawang Merah | G5: Brand A | H5: 30000 | I5: 3 | J5: 20 | K5: 90000 | L5: 18000 | M5: 72000 | N5: 15000 | O5: 87000 | P5: e-Wallet | Q5: Completed | R5: Toko Biru | S5: 4 | T5: Perempuan | U5: January | V5: 2025 | W5: 1
A6: ORD01549 | B6: 45658.607 | C6: Fitri Ramadhani | D6: Surabaya | E6: Telur Ayam - Brand C | F6: Telur Ayam | G6: Brand C | H6: 28000 | I6: 5 | J6: 5 | K6: 140000 | L6: 7000 | M6: 133000 | N6: 74000 | O6: 207000 | P6: COD | Q6: Completed | R6: TokTok | S6: 3 | T6: Perempuan | U6: January | V6: 2025 | W6: 1
A7: ORD01854 | B7: 45658.663 | C7: Tono Kurniawan | D7: Semarang | E7: Garam - Brand C | F7: Garam | G7: Brand C | H7: 6000 | I7: 4 | J7: 10 | K7: 24000 | L7: 2400 | M7: 21600 | N7: 76000 | O7: 97600 | P7: Transfer Bank | Q7: Returned | R7: Toko Orange | S7: 3 | T7: Laki-laki | U7: January | V7: 2025 | W7: 1
A8: ORD00642 | B8: 45658.794 | C8: Hendra Syahputra | D8: Wamena | E8: Telur Ayam - Brand A | F8: Telur Ayam | G8: Brand A | H8: 22000 | I8: 1 | J8: 10 | K8: 22000 | L8: 2200 | M8: 19800 | N8: 15000 | O8: 34800 | P8: COD | Q8: Completed | R8: Toko Ungu | S8: 1 | T8: Laki-laki | U8: January | V8: 2025 | W8: 1
A9: ORD01352 | B9: 45658.815 | C9: Indra Halim | D9: Tanjung Selor | E9: Gula Pasir - Brand C | F9: Gula Pasir | G9: Brand C | H9: 18000 | I9: 1 | J9: 5 | K9: 18000 | L9: 900 | M9: 17100 | N9: 26000 | O9: 43100 | P9: Transfer Bank | Q9: Completed | R9: Toko Ungu | S9: 5 | T9: Laki-laki | U9: January | V9: 2025 | W9: 1
A10: ORD00616 | B10: 45658.85 | C10: Wahyu Hidayat | D10: Wamena | E10: Garam - Brand A | F10: Garam | G10: Brand A | H10: 4000 | I10: 1 | J10: 20 | K10: 4000 | L10: 800 | M10: 3200 | N10: 15000 | O10: 18200 | P10: e-Wallet | Q10: Completed | R10: TokTok | S10: 3 | T10: Laki-laki | U10: January | V10: 2025 | W10: 1
A11: ORD00528 | B11: 45659.142 | C11: Zahra Setiawan | D11: Banjarbaru | E11: Gula Pasir - Brand B | F11: Gula Pasir | G11: Brand B | H11: 17000 | I11: 1 | J11: 10 | K11: 17000 | L11: 1700 | M11: 15300 | N11: 55000 | O11: 70300 | P11: Kartu Kredit | Q11: Returned | R11: Toko Orange | S11: 2 | T11: Perempuan | U11: January | V11: 2025 | W11: 1
A12: ORD00809 | B12: 45659.26 | C12: Yani Ananda | D12: Mataram | E12: Beras - Brand B | F12: Beras | G12: Brand B | H12: 15000 | I12: 2 | J12: 0 | K12: 30000 | L12: 0 | M12: 30000 | N12: 56000 | O12: 86000 | P12: e-Wallet | Q12: Completed | R12: Toko Hijau | S12: 1 | T12: Perempuan | U12: January | V12: 2025 | W12: 1
A13: ORD00413 | B13: 45659.448 | C13: Kartika Saputra | D13: Palu | E13: Gula Pasir - Brand A | F13: Gula Pasir | G13: Brand A | H13: 16000 | I13: 2 | J13: 10 | K13: 32000 | L13: 3200 | M13: 28800 | N13: 67000 | O13: 95800 | P13: Kartu Kredit | Q13: Completed | R13: Toko Ungu | S13: 3 | T13: Perempuan | U13: January | V13: 2025 | W13: 1
... A2001: ORD01065 | B2001: 45657.957 | C2001: Dewi Budiman | D2001: Kupang | E2001: Garam - Brand C | F2001: Garam | G2001: Brand C | H2001: 6000 | I2001: 3 | J2001: 20 | K2001: 18000 | L2001: 3600 | M2001: 14400 | N2001: 21000 | O2001: 35400 | P2001: COD | Q2001: Completed | R2001: TokTok | S2001: 5 | T2001: Perempuan | U2001: December | V2001: 2024 | W2001: 12

Sheet Dashboard Disa

Sheet Pivot
A1: Total Product Sale | C1: Total Sale | E1: Total Transaksi | G1: Penjualan Perbulan | L1: Product Terlaris | Q1: Brand Terlaris | V1: Jenis Platform | AC1: 15 Cust teratas | AH1: Cara Pembayaran | AN1: Penjualan/Tahun
A4: Sum of Quantity | C4: Sum of Total Sales | E4: Count of Order ID | G4: Row Labels | H4: Sum of Total Sales | J4: Sale | L4: Row Labels | M4: Sum of Quantity | Q4: Row Labels | R4: Sum of Quantity | V4: Row Labels | W4: Sum of Total Sales | Z4: =SUM(W5:W9) -> 128487050 | AC4: Row Labels | AD4: Sum of Total Sales | AH4: Row Labels | AI4: Sum of Total Sales | AL4: =SUM(AL5:AL8) -> 128487050 | AN4: Row Labels | AO4: Sum of Total Sales
A5: 5931 | C5: 128487050 | E5: 2000 | G5: January | H5: 10915900 | I5: =G5 -> January | J5: =H5 -> 10915900 | L5: Daging Ayam | M5: 719 | N5: =L5 -> Daging Ayam | O5: =M5 -> 719 | Q5: Brand B | R5: 1994 | S5: =Q5 -> Brand B | T5: =GETPIVOTDATA("Quantity",$Q$4,"Brand","Brand B") -> 1994 | V5: Toko Biru | W5: 25443450 | X5: Toko Biru | Y5: =Z5/$Z$4 -> 0.19802346 | Z5: =GETPIVOTDATA("Total Sales",$V$4,"Platform","Toko Biru") -> 25443450 | AC5: Kartika Saputra | AD5: 786800 | AE5: =AC5 -> Kartika Saputra | AF5: =AD5 -> 786800 | AH5: COD | AI5: 32878550 | AJ5: =AH5 -> COD | AK5: =AL5/$AL$4 -> 0.25588999 | AL5: =AI5 -> 32878550 | AN5: 2025 | AO5: 91706750
G6: February | H6: 8697300 | I6: =G6 -> February | J6: =H6 -> 8697300 | L6: Telur Ayam | M6: 706 | Q6: Brand A | R6: 1970 | V6: Toko Hijau | W6: 25596600 | X6: Toko Hijau | Y6: =Z6/$Z$4 -> 0.19921541 | Z6: =GETPIVOTDATA("Total Sales",$V$4,"Platform","Toko Hijau") -> 25596600 | AC6: Dewi Setiawan | AD6: 806600 | AE6: =AC6 -> Dewi Setiawan | AF6: =AD6 -> 806600 | AH6: e-Wallet | AI6: 29506400 | AJ6: =AH6 -> e-Wallet | AK6: =AL6/$AL$4 -> 0.22964493 | AL6: =AI6 -> 29506400 | AN6: 2024 | AO6: 36780300
G7: March | H7: 10043950 | I7: =G7 -> March | J7: =H7 -> 10043950 | L7: Garam | M7: 690 | Q7: Brand C | R7: 1967 | V7: Toko Orange | W7: 24925550 | X7: Toko Orange | Y7: =Z7/$Z$4 -> 0.1939927 | Z7: =GETPIVOTDATA("Total Sales",$V$4,"Platform","Toko Orange") -> 24925550 | AC7: Zahra Santoso | AD7: 809650 | AE7: =AC7 -> Zahra Santoso | AF7: =AD7 -> 809650 | AH7: Kartu Kredit | AI7: 32246800 | AJ7: =AH7 -> Kartu Kredit | AK7: =AL7/$AL$4 -> 0.25097315 | AL7: =AI7 -> 32246800
G8: April | H8: 10587550 | I8: =G8 -> April | J8: =H8 -> 10587550 | L8: Susu Bubuk | M8: 672 | Q8: Grand Total | R8: 5931 | V8: Toko Ungu | W8: 25860650 | X8: Toko Ungu | Y8: =Z8/$Z$4 -> 0.20127048 | Z8: =GETPIVOTDATA("Total Sales",$V$4,"Platform","Toko Ungu") -> 25860650 | AC8: Dewi Hidayat | AD8: 824800 | AE8: =AC8 -> Dewi Hidayat | AF8: =AD8 -> 824800 | AH8: Transfer Bank | AI8: 33855300 | AJ8: =AH8 -> Transfer Bank | AK8: =AL8/$AL$4 -> 0.26349192 | AL8: =AI8 -> 33855300
G9: May | H9: 11359600 | I9: =G9 -> May | J9: =H9 -> 11359600 | L9: Tepung Terigu | M9: 667 | V9: TokTok | W9: 26660800 | X9: TokTok | Y9: =Z9/$Z$4 -> 0.20749795 | Z9: =GETPIVOTDATA("Total Sales",$V$4,"Platform","TokTok") -> 26660800 | AC9: Nanda Iskandar | AD9: 846100 | AE9: =AC9 -> Nanda Iskandar | AF9: =AD9 -> 846100
G10: June | H10: 11708650 | I10: =G10 -> June | J10: =H10 -> 11708650 | L10: Gula Pasir | M10: 664 | AC10: Zahra Kurniawan | AD10: 859250 | AE10: =AC10 -> Zahra Kurniawan | AF10: =AD10 -> 859250
G11: July | H11: 12385950 | I11: =G11 -> July | J11: =H11 -> 12385950 | L11: Minyak Goreng | M11: 634 | AC11: Clara Utami | AD11: 895900 | AE11: =AC11 -> Clara Utami | AF11: =AD11 -> 895900
G12: August | H12: 11002900 | I12: =G12 -> August | J12: =H12 -> 11002900 | L12: Beras | M12: 624 | AC12: Aulia Iskandar | AD12: 897600 | AE12: =AC12 -> Aulia Iskandar | AF12: =AD12 -> 897600
G13: September | H13: 11962750 | I13: =G13 -> September | J13: =H13 -> 11962750 | L13: Bawang Merah | M13: 555 | AC13: Zahra Budiman | AD13: 947300 | AE13: =AC13 -> Zahra Budiman | AF13: =AD13 -> 947300
G14: October | H14: 10583650 | I14: =G14 -> October | J14: =H14 -> 10583650 | AC14: Ani Fauziah | AD14: 967300 | AE14: =AC14 -> Ani Fauziah | AF14: =AD14 -> 967300
G15: November | H15: 10883500 | I15: =G15 -> November | J15: =H15 -> 10883500 | AC15: Ani Hidayat | AD15: 1006300 | AE15: =AC15 -> Ani Hidayat | AF15: =AD15 -> 1006300
G16: December | H16: 8355350 | I16: =G16 -> December | J16: =H16 -> 8355350 | AC16: Hana Nugroho | AD16: 1067200 | AE16: =AC16 -> Hana Nugroho | AF16: =AD16 -> 1067200
AC17: Yani Ananda | AD17: 1136350 | AE17: =AC17 -> Yani Ananda | AF17: =AD17 -> 1136350
AC18: Sari Puspita | AD18: 1197750 | AE18: =AC18 -> Sari Puspita | AF18: =AD18 -> 1197750
AC19: Citra Maulana | AD19: 1206200 | AE19: =AC19 -> Citra Maulana | AF19: =AD19 -> 1206200
